Metadata-Version: 2.1
Name: pwnage
Version: 1.0.0
Summary: CLI tool for https://haveibeenpwned.com
Home-page: https://github.com/zloether/Pwnage
Author: Zackary Loether
Author-email: zloether@gmail.com
License: MIT
Keywords: password hibp pwned
Platform: UNKNOWN
Classifier: Programming Language :: Python
Classifier: Programming Language :: Python :: 3
Classifier: Programming Language :: Python :: 3.5
Classifier: Programming Language :: Python :: 3.6
Classifier: Programming Language :: Python :: 3.7
Classifier: Topic :: Utilities
Classifier: License :: OSI Approved :: MIT License
Classifier: Development Status :: 5 - Production/Stable
